README.md
setup.py
xripl/__init__.py
xripl/clean.py
xripl/contour.py
xripl/contrast.py
xripl/films.py
xripl/filters.py
xripl/instrument.py
xripl/magnification.py
xripl/pltDefaults.py
xripl/reader.py
xripl/segmentation.py
xripl/tubeTransmission.py
xripl/visualizations.py
xripl.egg-info/PKG-INFO
xripl.egg-info/SOURCES.txt
xripl.egg-info/dependency_links.txt
xripl.egg-info/not-zip-safe
xripl.egg-info/top_level.txt