Metadata-Version: 2.1
Name: xripl
Version: 0.2.0
Summary: X-Ray Radiographic Image Processing Library
Home-page: https://github.com/lanl/xripl
Author: Pawel Marek Kozlowski
Author-email: pkozlowski@lanl.gov
License: BSD
Platform: UNKNOWN
Classifier: Intended Audience :: Science/Research
Classifier: License :: OSI Approved :: BSD License
Classifier: Development Status :: 3 - Alpha
Classifier: Operating System :: OS Independent
Classifier: Programming Language :: Python :: 3
Classifier: Topic :: Scientific/Engineering :: Physics
Classifier: Topic :: Scientific/Engineering :: Image Processing
Classifier: Natural Language :: English
